home_assistant_plugin/__init__.py
home_assistant_plugin/gateway.py
home_assistant_plugin/message.py
home_assistant_plugin/factory/__init__.py
home_assistant_plugin/factory/trigger.py
home_assistant_plugin/service/__init__.py
home_assistant_plugin/service/trigger.py
home_assistant_plugin/service/media_player/__init__.py
home_assistant_plugin/service/media_player/command.py
home_assistant_plugin/service/media_player/trigger.py
home_assistant_plugin/service/notify/__init__.py
home_assistant_plugin/service/notify/command.py
home_assistant_plugin/service/sensor/__init__.py
home_assistant_plugin/service/sensor/trigger.py
home_assistant_plugin/service/sensor/float/__init__.py
home_assistant_plugin/service/sensor/float/trigger.py
home_assistant_plugin/tests/__init__.py
home_assistant_plugin/tests/test_doctests.py
automate_home_assistant_plugin-0.9.1.dist-info/METADATA
automate_home_assistant_plugin-0.9.1.dist-info/WHEEL
automate_home_assistant_plugin-0.9.1.dist-info/top_level.txt
automate_home_assistant_plugin-0.9.1.dist-info/RECORD
